benchmark_utils/__init__.py
benchmark_utils/benchmark.py
benchmark_utils/version.py
"benchmark_utils/version.py,cover"
benchmark_utils-0.2.5.dist-info/WHEEL
benchmark_utils-0.2.5.dist-info/METADATA
benchmark_utils-0.2.5.dist-info/RECORD
