Metadata-Version: 2.3
Name: benchmark_utils
Version: 0.2.5
Summary: Utils for benchmark.
Author: Yasyrev Andrei
Author-email: Yasyrev Andrei <a.yasyrev@gmail.com>
License: Apache-2.0
Classifier: Programming Language :: Python :: 3.10
Classifier: Programming Language :: Python :: 3.11
Classifier: Programming Language :: Python :: 3.12
Classifier: Programming Language :: Python :: 3.13
Classifier: Programming Language :: Python :: 3.14
Classifier: License :: OSI Approved :: Apache Software License
Classifier: Operating System :: OS Independent
Requires-Dist: rich
Requires-Dist: tomli>=2.0.0 ; python_full_version < '3.11'
Requires-Dist: coverage[toml] ; extra == 'dev'
Requires-Dist: mypy ; extra == 'dev'
Requires-Dist: nbmetaclean ; extra == 'dev'
Requires-Dist: nox ; extra == 'dev'
Requires-Dist: pre-commit ; extra == 'dev'
Requires-Dist: ruff ; extra == 'dev'
Requires-Dist: pytest ; extra == 'test'
Requires-Dist: pytest-cov ; extra == 'test'
Requires-Python: >=3.10, <3.15
Project-URL: Homepage, https://github.com/ayasyrev/benchmark_utils
Project-URL: Repository, https://github.com/ayasyrev/benchmark_utils
Provides-Extra: dev
Provides-Extra: test
